skmlm/__init__.py
skmlm/mlm.py
skmlm/utils.py
scikit_mlm-0.1.1.dist-info/LICENSE
scikit_mlm-0.1.1.dist-info/METADATA
scikit_mlm-0.1.1.dist-info/WHEEL
scikit_mlm-0.1.1.dist-info/top_level.txt
scikit_mlm-0.1.1.dist-info/RECORD
