Metadata-Version: 2.1
Name: scikit-mlm
Version: 0.1.1
Summary: Minimal Learning Machine implementation using the scikit-learn API
Home-page: https://github.com/omadson/scikit-mlm
Author: Madson Dias
Author-email: madsonddias@gmail.com
License: MIT
Platform: UNKNOWN
Classifier: Development Status :: 3 - Alpha
Classifier: License :: OSI Approved :: BSD License
Classifier: Operating System :: OS Independent
Classifier: Programming Language :: Python :: 3.5
Requires-Dist: numpy (>=1.15.4)
Requires-Dist: scipy (>=1.1.0)
Requires-Dist: scikit-learn (>=0.21.0)
Requires-Dist: fuzzy-c-means (>=0.0.6)
Requires-Dist: mrsr (>=0.0.3)
